etl_pbshop/__init__.py
etl_pbshop/config_model.py
etl_pbshop/connectors.py
etl_pbshop/etl_model.py
etl_pbshop/helper.py
etl_pbshop/query_model.py
etl_pbshop/visualization.py
etl_pbshop-0.3.0.dist-info/LICENSE
etl_pbshop-0.3.0.dist-info/METADATA
etl_pbshop-0.3.0.dist-info/WHEEL
etl_pbshop-0.3.0.dist-info/top_level.txt
etl_pbshop-0.3.0.dist-info/RECORD
