Metadata-Version: 2.1
Name: etl-pbshop
Version: 0.3.0
Summary: Create your ETL integrations easy and quick!
Home-page: http://dscar.ga/etl_pbshop_lib
Author: Daniel S. Camargo
Author-email: daniel.supervisao@gmail.com
License: UNKNOWN
Platform: UNKNOWN
Classifier: Programming Language :: Python :: 3
Classifier: License :: OSI Approved :: MIT License
Classifier: Operating System :: OS Independent
Requires-Python: >=3.6
Requires-Dist: pydot
Requires-Dist: pytz
Requires-Dist: google-api-python-client
Requires-Dist: google-auth-httplib2
Requires-Dist: google-auth-oauthlib
Requires-Dist: pygsheets
Requires-Dist: simple-salesforce
Requires-Dist: requests
Requires-Dist: boto3
Requires-Dist: pandas
